martinpykit/utils/__init__.py
martinpykit/utils/http.py
martinpykit-0.1.1.dist-info/LICENSE
martinpykit-0.1.1.dist-info/METADATA
martinpykit-0.1.1.dist-info/WHEEL
martinpykit-0.1.1.dist-info/top_level.txt
martinpykit-0.1.1.dist-info/RECORD
