Metadata-Version: 2.2
Name: martinpykit
Version: 0.1.1
Summary: A powerful Python utilities package
Author-email: fbbyqsyea <fbbyqsyea@163.com>
License: MIT License
Project-URL: Homepage, https://github.com/fbbyqsyea/martinpykit
Requires-Python: >=3.7
License-File: LICENSE
Requires-Dist: httpx>=0.28.1
Provides-Extra: dev
Requires-Dist: pytest>=8.3.5; extra == "dev"
Requires-Dist: pytest-asyncio>=0.25.3; extra == "dev"
Requires-Dist: black; extra == "dev"
